ecophylo/__init__.py
ecophylo/dosimulate.py
ecophylo/islmodel.py
ecophylo/islmodel_mugger.py
ecophylo/pastdemo.py
ecophylo/phylogen.py
ecophylo/sumstat.py
ecophylo/toPhylo.py
ecophylo-0.1.6.dist-info/LICENSE
ecophylo-0.1.6.dist-info/METADATA
ecophylo-0.1.6.dist-info/WHEEL
ecophylo-0.1.6.dist-info/top_level.txt
ecophylo-0.1.6.dist-info/RECORD
