Metadata-Version: 2.1
Name: ecophylo
Version: 0.1.6
Summary: Coalescent-based simulations of eco-evolutionary biodiverity dynamics
Home-page: https://github.com/thegreatlizzyator/ecophylo
Author: Elizabeth Barthelemy
Author-email: elizabeth.barthelemy@univ-grenoble-alpes.fr
License: CeCILL
Platform: UNKNOWN
Classifier: Development Status :: 4 - Beta
Classifier: Intended Audience :: Science/Research
Classifier: Programming Language :: Python :: 3.7
Classifier: License :: CeCILL-B Free Software License Agreement (CECILL-B)
Classifier: Operating System :: OS Independent
Requires-Python: >=3.7
Requires-Dist: setuptools
Requires-Dist: requests
